.gitignore
.long-description.html
CHANGES.txt
MANIFEST.in
README.rst
bootstrap.py
buildout.cfg
setup.py
src/pythonpackages/__init__.py
src/pythonpackages.sendpickedversions.egg-info/PKG-INFO
src/pythonpackages.sendpickedversions.egg-info/SOURCES.txt
src/pythonpackages.sendpickedversions.egg-info/dependency_links.txt
src/pythonpackages.sendpickedversions.egg-info/entry_points.txt
src/pythonpackages.sendpickedversions.egg-info/namespace_packages.txt
src/pythonpackages.sendpickedversions.egg-info/not-zip-safe
src/pythonpackages.sendpickedversions.egg-info/requires.txt
src/pythonpackages.sendpickedversions.egg-info/top_level.txt
src/pythonpackages/sendpickedversions/__init__.py
src/pythonpackages/sendpickedversions/pickedversions.txt
src/pythonpackages/sendpickedversions/tests.py