Metadata-Version: 1.1
Name: pythonpackages.sendpickedversions
Version: 0.0.1
Summary: Sends picked packages and versions to a whiskers server.
Home-page: http://github.com/pythonpackages/pythonpackages.sendpickedversions
Author: Alex Clark (fork author)
Author-email: aclark@aclark.net
License: GPL
Keywords: buildout extension send picked versions
Platform: UNKNOWN
Classifier: Framework :: Buildout
Classifier: Intended Audience :: Developers
Classifier: Topic :: Software Development :: Build Tools
Classifier: Topic :: Software Development :: Libraries :: Python Modules
